pbxproj/PBXGenericObject.py
pbxproj/PBXKey.py
pbxproj/PBXList.py
pbxproj/PBXObjects.py
pbxproj/PBXRootObject.py
pbxproj/XcodeProject.py
pbxproj/__init__.py
pbxproj/__main__.py
pbxproj/pbxcli/__init__.py
pbxproj/pbxcli/pbxproj_file.py
pbxproj/pbxcli/pbxproj_flag.py
pbxproj/pbxcli/pbxproj_folder.py
pbxproj/pbxcli/pbxproj_show.py
pbxproj/pbxextensions/ProjectFiles.py
pbxproj/pbxextensions/ProjectFlags.py
pbxproj/pbxextensions/ProjectGroups.py
pbxproj/pbxextensions/__init__.py
pbxproj/pbxsections/PBXAggregateTarget.py
pbxproj/pbxsections/PBXBuildFile.py
pbxproj/pbxsections/PBXContainerItemProxy.py
pbxproj/pbxsections/PBXCopyFilesBuildPhase.py
pbxproj/pbxsections/PBXFileReference.py
pbxproj/pbxsections/PBXFileSystemSynchronizedRootGroup.py
pbxproj/pbxsections/PBXFrameworksBuildPhase.py
pbxproj/pbxsections/PBXGenericBuildPhase.py
pbxproj/pbxsections/PBXGenericTarget.py
pbxproj/pbxsections/PBXGroup.py
pbxproj/pbxsections/PBXHeadersBuildPhase.py
pbxproj/pbxsections/PBXLegacyTarget.py
pbxproj/pbxsections/PBXNativeTarget.py
pbxproj/pbxsections/PBXProject.py
pbxproj/pbxsections/PBXReferenceProxy.py
pbxproj/pbxsections/PBXResourcesBuildPhase.py
pbxproj/pbxsections/PBXShellScriptBuildPhase.py
pbxproj/pbxsections/PBXSourcesBuildPhase.py
pbxproj/pbxsections/PBXTargetDependency.py
pbxproj/pbxsections/XCBuildConfiguration.py
pbxproj/pbxsections/XCConfigurationList.py
pbxproj/pbxsections/XCLocalSwiftPackageReference.py
pbxproj/pbxsections/XCRemoteSwiftPackageReference.py
pbxproj/pbxsections/XCSwiftPackageProductDependency.py
pbxproj/pbxsections/__init__.py
pbxproj-4.3.2.dist-info/METADATA
pbxproj-4.3.2.dist-info/WHEEL
pbxproj-4.3.2.dist-info/entry_points.txt
pbxproj-4.3.2.dist-info/top_level.txt
pbxproj-4.3.2.dist-info/RECORD
