Metadata-Version: 2.4
Name: pbxproj
Version: 4.3.2
Summary: XCode Project manipulation library for Python
Home-page: http://github.com/kronenthaler/mod-pbxproj
Author: Ignacio Calderon
License-Expression: MIT
Requires-Python: >=3.10
Requires-Dist: docopt
Requires-Dist: openstep-parser>=2.0.2
Dynamic: home-page
